{
  "rubric_id": "rubric-mr03-validacio-errors",
  "challenge_id": "mr03-validacio-errors",
  "max_score": 10,
  "dimensions": [
    { "id": "functional_resolution", "label": "Resolució funcional", "weight": 0.3, "must_check": "Diferencia casos vàlids i invàlids." },
    { "id": "verification", "label": "Verificació", "weight": 0.25, "must_check": "Prova cas vàlid i invàlid." },
    { "id": "traceability", "label": "Traçabilitat", "weight": 0.1, "must_check": "Regles localitzables." },
    { "id": "documentation", "label": "Documentació", "weight": 0.1, "must_check": "Documenta regles i proves." },
    { "id": "ai_usage", "label": "Ús d'IA", "weight": 0.1, "must_check": "Registre d'IA si és requerit." },
    { "id": "code_quality", "label": "Qualitat del codi", "weight": 0.15, "must_check": "Errors tractats sense fallades fatals." }
  ],
  "hard_rules": ["Sense prova de cas invàlid, puntuació màxima recomanada 6."]
}
